configtor.py
configtor-0.0.2.dist-info/entry_points.txt
configtor-0.0.2.dist-info/LICENSE
configtor-0.0.2.dist-info/WHEEL
configtor-0.0.2.dist-info/METADATA
configtor-0.0.2.dist-info/RECORD
