Metadata-Version: 2.1
Name: configtor
Version: 0.0.2
Summary: configuration tool base on jinja2
Home-page: UNKNOWN
License: UNKNOWN
Author: ChienHsiao
Author-email: chien.hsiao@revteltech.com
Classifier: License :: OSI Approved :: MIT License
Requires-Dist: Jinja2
Requires-Dist: typer
